pylovens/__init__.py
pylovens/_version.py
pylovens/client.py
pylovens/exceptions.py
pylovens/py.typed
pylovens-0.3.1.dist-info/LICENSE
pylovens-0.3.1.dist-info/METADATA
pylovens-0.3.1.dist-info/WHEEL
pylovens-0.3.1.dist-info/top_level.txt
pylovens-0.3.1.dist-info/RECORD
