Metadata-Version: 2.1
Name: pylovens
Version: 0.3.1
Summary: Python client for the Lovens API.
Author-email: Rogier van der Geer <rogier@vander-geer.nl>
License: MIT
Project-URL: Repository, https://github.com/rogiervandergeer/pylovens
Keywords: api,cargo bike,ebike,gps,lovens
Classifier: Intended Audience :: Developers
Classifier: License :: OSI Approved :: MIT License
Classifier: Operating System :: OS Independent
Classifier: Programming Language :: Python :: 3
Classifier: Typing :: Typed
Requires-Python: >=3.10
License-File: LICENSE
Requires-Dist: requests >=2.31.0
Provides-Extra: dev
Requires-Dist: black ==23.3.0 ; extra == 'dev'
Requires-Dist: pre-commit >=3.3.3 ; extra == 'dev'
Requires-Dist: pytest >=7.3.1 ; extra == 'dev'
Requires-Dist: pytest-mock >=3.11.0 ; extra == 'dev'
